swarmops/DE.py
swarmops/FitnessTrace.py
swarmops/LUS.py
swarmops/LogSolutions.py
swarmops/MetaOptimize.py
swarmops/Optimize.py
swarmops/PS.py
swarmops/PSO.py
swarmops/Problem.py
swarmops/Timer.py
swarmops/__init__.py
swarmops/tools.py
swarmops-1.0.0.dist-info/METADATA
swarmops-1.0.0.dist-info/RECORD
swarmops-1.0.0.dist-info/WHEEL
swarmops-1.0.0.dist-info/top_level.txt
